README
setup.py
recipe/__init__.py
recipe/recipe.py
recipe_new_project.egg-info/PKG-INFO
recipe_new_project.egg-info/SOURCES.txt
recipe_new_project.egg-info/dependency_links.txt
recipe_new_project.egg-info/not-zip-safe
recipe_new_project.egg-info/top_level.txt