Metadata-Version: 1.0
Name: recipe-new-project
Version: 0.1
Summary: New python project recipe
Home-page: http://github.com/nuidi-dev/recipe
Author: ZZI
Author-email: hi@nuidi.com
License: MIT
Platform: UNKNOWN
